odoo/addons/currency_rate_update_by_nbb/README.rst
odoo/addons/currency_rate_update_by_nbb/__init__.py
odoo/addons/currency_rate_update_by_nbb/__manifest__.py
odoo/addons/currency_rate_update_by_nbb/i18n/currency_rate_update_by_nbb.pot
odoo/addons/currency_rate_update_by_nbb/readme/CONFIGURE.rst
odoo/addons/currency_rate_update_by_nbb/readme/CONTRIBUTORS.rst
odoo/addons/currency_rate_update_by_nbb/readme/CREDITS.rst
odoo/addons/currency_rate_update_by_nbb/readme/DESCRIPTION.rst
odoo/addons/currency_rate_update_by_nbb/readme/INSTALL.rst
odoo/addons/currency_rate_update_by_nbb/services/__init__.py
odoo/addons/currency_rate_update_by_nbb/services/update_service_by_nbb.py
odoo/addons/currency_rate_update_by_nbb/static/description/icon.png
odoo/addons/currency_rate_update_by_nbb/static/description/index.html
odoo11_addon_currency_rate_update_by_nbb-11.0.1.0.0.99.dev5.dist-info/METADATA
odoo11_addon_currency_rate_update_by_nbb-11.0.1.0.0.99.dev5.dist-info/WHEEL
odoo11_addon_currency_rate_update_by_nbb-11.0.1.0.0.99.dev5.dist-info/top_level.txt
odoo11_addon_currency_rate_update_by_nbb-11.0.1.0.0.99.dev5.dist-info/RECORD
